.VERSION
AUTHORS.rst
CONTRIBUTING.rst
HISTORY.rst
LICENSE
MANIFEST.in
Pipfile
Pipfile.lock
README.rst
USAGE.rst
dev-requirements.txt
requirements.txt
setup.cfg
setup.py
docs/Makefile
docs/authors.rst
docs/conf.py
docs/contributing.rst
docs/history.rst
docs/index.rst
docs/installation.rst
docs/modules.rst
docs/readme.rst
docs/terraformlintingcli.rst
docs/usage.rst
terraformlintingcli/.VERSION
terraformlintingcli/__init__.py
terraformlintingcli/_version.py
terraformlintingcli/terraformlintingcli.py
terraformlintingcli/terraformlintingcliexceptions.py
terraformlintingcli.egg-info/PKG-INFO
terraformlintingcli.egg-info/SOURCES.txt
terraformlintingcli.egg-info/dependency_links.txt
terraformlintingcli.egg-info/entry_points.txt
terraformlintingcli.egg-info/not-zip-safe
terraformlintingcli.egg-info/requires.txt
terraformlintingcli.egg-info/top_level.txt