Metadata-Version: 1.1
Name: terraformlintingcli
Version: 0.1.0
Summary: A cli to lint and check file positioning for terraform resources
Home-page: https://github.com/schubergphilis/terraformlintingcli.git
Author: Costas Tyfoxylos
Author-email: ctyfoxylos@schubergphilis.com
License: MIT
Keywords: terraformlintingcli terraform linting position checking cli
Platform: UNKNOWN
Classifier: Development Status :: 4 - Beta
Classifier: Intended Audience :: Developers
Classifier: License :: OSI Approved :: MIT License
Classifier: Natural Language :: English
Classifier: Programming Language :: Python :: 2.7
